aiopsutil/__init__.py
aiopsutil/aiopsutil.py
aiopsutil-0.1.0.dist-info/LICENSE
aiopsutil-0.1.0.dist-info/METADATA
aiopsutil-0.1.0.dist-info/WHEEL
aiopsutil-0.1.0.dist-info/top_level.txt
aiopsutil-0.1.0.dist-info/zip-safe
aiopsutil-0.1.0.dist-info/RECORD
