Metadata-Version: 2.2
Name: aiopsutil
Version: 0.1.0
Summary: aiopsutil is an asynchronous version of the popular psutil library, designed to provide an efficient and non-blocking way to retrieve information on running processes and system utilization.
Author-email: 解文 <2965312076@qq.com>
License: BSD 3-Clause License
Project-URL: repository, https://github.com/nostalgiatan/aiopsutil-python
Project-URL: Bug Reports, https://github.com/nostalgiatan/aiopsutil-python/issues
Keywords: aiopsutil,async psutil,psutil
Classifier: Development Status :: 5 - Production/Stable
Classifier: Intended Audience :: Developers
Classifier: License :: OSI Approved :: BSD License
Classifier: Operating System :: OS Independent
Classifier: Programming Language :: Python :: 3
Classifier: Programming Language :: Python :: 3.8
Classifier: Programming Language :: Python :: 3.9
Classifier: Programming Language :: Python :: 3.10
Classifier: Programming Language :: Python :: 3.11
Classifier: Programming Language :: Python :: 3.12
Classifier: Programming Language :: Python :: 3.13
Requires-Python: >=3.6
License-File: LICENSE
Requires-Dist: psutil
